{"cameraMode":{"drawMode":0,"name":"Shaded","section":"Shading Mode"},"sceneLighting":true,"audioPlay":false,"sceneViewState":{"showFog":true,"showMaterialUpdate":false,"showSkybox":true,"showFlares":true,"showImageEffects":true,"showParticleSystems":true},"in2DMode":false,"pivot":{"x":122.05503845214844,"y":808.2391967773438,"z":72.2490234375},"rotation":{"x":0.022667717188596727,"y":0.9665482044219971,"z":-0.23838511109352113,"w":0.09190510958433151},"size":147.72128295898438,"orthographic":false}